axoproj/__init__.py
axoproj/classes.py
axoproj/funcs.py
axoproj-0.0.5.dist-info/LICENSE
axoproj-0.0.5.dist-info/METADATA
axoproj-0.0.5.dist-info/WHEEL
axoproj-0.0.5.dist-info/top_level.txt
axoproj-0.0.5.dist-info/RECORD
