Metadata-Version: 2.1
Name: axoproj
Version: 0.0.5
Summary: A code to create datacubes from simple models
Home-page: https://github.com/Alois-deValon/Axoproj
Author: A. de Valon
Author-email: aloisdevalon@gmail.com
License: GPL-3.0
Platform: UNKNOWN
Classifier: License :: OSI Approved :: GNU General Public License v3 (GPLv3)
Classifier: Programming Language :: Python :: 3
Classifier: Programming Language :: Python :: 3 :: Only
Classifier: Programming Language :: Python :: 3.7
Classifier: Programming Language :: Python :: 3.8
Classifier: Programming Language :: Python :: 3.9
Classifier: Programming Language :: Python :: 3.10
Requires-Python: >=3.7
Requires-Dist: matplotlib (>=3.4.2)
Requires-Dist: numpy (>=1.15.0)
Requires-Dist: scipy (>=1.1.0)
Requires-Dist: tqdm (>=4.24.0)
